beibo.py
beibo-0.1.1.dist-info/METADATA
beibo-0.1.1.dist-info/WHEEL
beibo-0.1.1.dist-info/top_level.txt
beibo-0.1.1.dist-info/RECORD
