Metadata-Version: 2.1
Name: beibo
Version: 0.1.1
Summary: 🤖 Predict the stock market with AI 用AI预测股票市场
Home-page: https://github.com/ssantoshp/Beibo
Author: Santosh Passoubady
Author-email: santoshpassoubady@gmail.com
License: MIT
Platform: UNKNOWN
Requires-Dist: darts
Requires-Dist: yfinance
